pydockermon/__init__.py
pydockermon-0.0.2.dist-info/METADATA
pydockermon-0.0.2.dist-info/RECORD
pydockermon-0.0.2.dist-info/WHEEL
pydockermon-0.0.2.dist-info/top_level.txt
