Metadata-Version: 2.1
Name: pydockermon
Version: 0.0.2
Summary: A python module to interact with ha-dockermon.
Home-page: https://gitlab.com/ludeeus/pydockermon
Author: Joakim Sorensen
Author-email: joasoe@gmail.com
License: UNKNOWN
Platform: UNKNOWN
Classifier: Programming Language :: Python :: 3
Classifier: License :: OSI Approved :: MIT License
Classifier: Operating System :: OS Independent
